{
    "coord": {
        "lon": -73.5878,
        "lat": 45.5088
    },
    "weather": [
        {
            "id": 601,
            "main": "Snow",
            "description": "snow",
            "icon": "13n"
        }
    ],
    "base": "stations",
    "main": {
        "temp": -12.43,
        "feels_like": -19.43,
        "temp_min": -13.1,
        "temp_max": -11.71,
        "pressure": 1022,
        "humidity": 79,
        "sea_level": 1022,
        "grnd_level": 1018
    },
    "visibility": 4828,
    "wind": {
        "speed": 8.23,
        "deg": 50,
        "gust": 12.35
    },
    "snow": {
        "1h": 0.88
    },
    "clouds": {
        "all": 100
    },
    "dt": 1739428963,
    "sys": {
        "type": 1,
        "id": 498,
        "country": "CA",
        "sunrise": 1739447942,
        "sunset": 1739485098
    },
    "timezone": -18000,
    "id": 6077243,
    "name": "Montreal",
    "cod": 200
}