{
    "coord": {
        "lon": -73.5878,
        "lat": 45.5088
    },
    "weather": [
        {
            "id": 800,
            "main": "Clear",
            "description": "clear sky",
            "icon": "01n"
        }
    ],
    "base": "stations",
    "main": {
        "temp": 13.75,
        "feels_like": 12.43,
        "temp_min": 11.56,
        "temp_max": 14.67,
        "pressure": 1029,
        "humidity": 48,
        "sea_level": 1029,
        "grnd_level": 1026
    },
    "visibility": 10000,
    "wind": {
        "speed": 0.51,
        "deg": 260
    },
    "clouds": {
        "all": 0
    },
    "dt": 1779504179,
    "sys": {
        "type": 1,
        "id": 498,
        "country": "CA",
        "sunrise": 1779441399,
        "sunset": 1779495942
    },
    "timezone": -14400,
    "id": 6077243,
    "name": "Montreal",
    "cod": 200
}