{
    "coord": {
        "lon": -73.5878,
        "lat": 45.5088
    },
    "weather": [
        {
            "id": 803,
            "main": "Clouds",
            "description": "broken clouds",
            "icon": "04n"
        }
    ],
    "base": "stations",
    "main": {
        "temp": -2.65,
        "feels_like": -6.77,
        "temp_min": -4.21,
        "temp_max": -1.99,
        "pressure": 1029,
        "humidity": 60,
        "sea_level": 1029,
        "grnd_level": 1025
    },
    "visibility": 10000,
    "wind": {
        "speed": 3.09,
        "deg": 240
    },
    "clouds": {
        "all": 75
    },
    "dt": 1774750861,
    "sys": {
        "type": 1,
        "id": 498,
        "country": "CA",
        "sunrise": 1774694529,
        "sunset": 1774739786
    },
    "timezone": -14400,
    "id": 6077243,
    "name": "Montreal",
    "cod": 200
}