{
    "coord": {
        "lon": -73.5878,
        "lat": 45.5088
    },
    "weather": [
        {
            "id": 803,
            "main": "Clouds",
            "description": "broken clouds",
            "icon": "04n"
        }
    ],
    "base": "stations",
    "main": {
        "temp": -6.66,
        "feels_like": -9.43,
        "temp_min": -10.03,
        "temp_max": -5.48,
        "pressure": 1016,
        "humidity": 68,
        "sea_level": 1016,
        "grnd_level": 1012
    },
    "visibility": 10000,
    "wind": {
        "speed": 1.54,
        "deg": 80
    },
    "clouds": {
        "all": 75
    },
    "dt": 1771466063,
    "sys": {
        "type": 1,
        "id": 943,
        "country": "CA",
        "sunrise": 1771415500,
        "sunset": 1771453511
    },
    "timezone": -18000,
    "id": 6077243,
    "name": "Montreal",
    "cod": 200
}