{
    "coord": {
        "lon": -73.5878,
        "lat": 45.5088
    },
    "weather": [
        {
            "id": 501,
            "main": "Rain",
            "description": "moderate rain",
            "icon": "10d"
        }
    ],
    "base": "stations",
    "main": {
        "temp": 2.99,
        "feels_like": -3.3,
        "temp_min": 2.3,
        "temp_max": 4.02,
        "pressure": 1003,
        "humidity": 73,
        "sea_level": 1003,
        "grnd_level": 999
    },
    "visibility": 10000,
    "wind": {
        "speed": 10.8,
        "deg": 180,
        "gust": 16.98
    },
    "rain": {
        "1h": 2.37
    },
    "clouds": {
        "all": 100
    },
    "dt": 1740435007,
    "sys": {
        "type": 2,
        "id": 2095341,
        "country": "CA",
        "sunrise": 1740397278,
        "sunset": 1740436446
    },
    "timezone": -18000,
    "id": 6077243,
    "name": "Montreal",
    "cod": 200
}