{
    "coord": {
        "lon": -73.5878,
        "lat": 45.5088
    },
    "weather": [
        {
            "id": 804,
            "main": "Clouds",
            "description": "overcast clouds",
            "icon": "04d"
        }
    ],
    "base": "stations",
    "main": {
        "temp": 15.95,
        "feels_like": 15.77,
        "temp_min": 14.96,
        "temp_max": 16.9,
        "pressure": 1005,
        "humidity": 83,
        "sea_level": 1005,
        "grnd_level": 1001
    },
    "visibility": 10000,
    "wind": {
        "speed": 0.89,
        "deg": 203,
        "gust": 1.79
    },
    "clouds": {
        "all": 100
    },
    "dt": 1745078956,
    "sys": {
        "type": 2,
        "id": 2095341,
        "country": "CA",
        "sunrise": 1745056877,
        "sunset": 1745106307
    },
    "timezone": -14400,
    "id": 6077243,
    "name": "Montreal",
    "cod": 200
}