{
    "coord": {
        "lon": -73.5878,
        "lat": 45.5088
    },
    "weather": [
        {
            "id": 803,
            "main": "Clouds",
            "description": "broken clouds",
            "icon": "04n"
        }
    ],
    "base": "stations",
    "main": {
        "temp": -0.2,
        "feels_like": -3.82,
        "temp_min": -1.65,
        "temp_max": 0.67,
        "pressure": 1013,
        "humidity": 61,
        "sea_level": 1013,
        "grnd_level": 1009
    },
    "visibility": 10000,
    "wind": {
        "speed": 3.09,
        "deg": 70
    },
    "clouds": {
        "all": 75
    },
    "dt": 1744012812,
    "sys": {
        "type": 1,
        "id": 498,
        "country": "CA",
        "sunrise": 1744021366,
        "sunset": 1744068577
    },
    "timezone": -14400,
    "id": 6077243,
    "name": "Montreal",
    "cod": 200
}