{
    "coord": {
        "lon": -73.5878,
        "lat": 45.5088
    },
    "weather": [
        {
            "id": 601,
            "main": "Snow",
            "description": "snow",
            "icon": "13n"
        }
    ],
    "base": "stations",
    "main": {
        "temp": -9.07,
        "feels_like": -16.07,
        "temp_min": -10.54,
        "temp_max": -7.52,
        "pressure": 1014,
        "humidity": 91,
        "sea_level": 1014,
        "grnd_level": 1010
    },
    "visibility": 1006,
    "wind": {
        "speed": 6.69,
        "deg": 60
    },
    "snow": {
        "1h": 1.78
    },
    "clouds": {
        "all": 100
    },
    "dt": 1739444538,
    "sys": {
        "type": 1,
        "id": 498,
        "country": "CA",
        "sunrise": 1739447942,
        "sunset": 1739485098
    },
    "timezone": -18000,
    "id": 6077243,
    "name": "Montreal",
    "cod": 200
}