{
    "coord": {
        "lon": -73.5878,
        "lat": 45.5088
    },
    "weather": [
        {
            "id": 803,
            "main": "Clouds",
            "description": "broken clouds",
            "icon": "04n"
        }
    ],
    "base": "stations",
    "main": {
        "temp": -5.84,
        "feels_like": -12.84,
        "temp_min": -6.74,
        "temp_max": -5.33,
        "pressure": 1007,
        "humidity": 79,
        "sea_level": 1007,
        "grnd_level": 1004
    },
    "visibility": 10000,
    "wind": {
        "speed": 10.29,
        "deg": 240,
        "gust": 15.95
    },
    "clouds": {
        "all": 75
    },
    "dt": 1768873064,
    "sys": {
        "type": 1,
        "id": 498,
        "country": "CA",
        "sunrise": 1768825678,
        "sunset": 1768858908
    },
    "timezone": -18000,
    "id": 6077243,
    "name": "Montreal",
    "cod": 200
}