{
    "coord": {
        "lon": -73.5878,
        "lat": 45.5088
    },
    "weather": [
        {
            "id": 803,
            "main": "Clouds",
            "description": "broken clouds",
            "icon": "04d"
        }
    ],
    "base": "stations",
    "main": {
        "temp": 0.29,
        "feels_like": -4.91,
        "temp_min": -0.52,
        "temp_max": 0.67,
        "pressure": 1012,
        "humidity": 72,
        "sea_level": 1012,
        "grnd_level": 1008
    },
    "visibility": 10000,
    "wind": {
        "speed": 5.66,
        "deg": 350
    },
    "clouds": {
        "all": 75
    },
    "dt": 1740587741,
    "sys": {
        "type": 1,
        "id": 498,
        "country": "CA",
        "sunrise": 1740569870,
        "sunset": 1740609415
    },
    "timezone": -18000,
    "id": 6077243,
    "name": "Montreal",
    "cod": 200
}