{
    "coord": {
        "lon": -73.5878,
        "lat": 45.5088
    },
    "weather": [
        {
            "id": 803,
            "main": "Clouds",
            "description": "broken clouds",
            "icon": "04d"
        }
    ],
    "base": "stations",
    "main": {
        "temp": -1.31,
        "feels_like": -7.2,
        "temp_min": -2.19,
        "temp_max": -0.88,
        "pressure": 1015,
        "humidity": 69,
        "sea_level": 1015,
        "grnd_level": 1012
    },
    "visibility": 10000,
    "wind": {
        "speed": 6.17,
        "deg": 270
    },
    "clouds": {
        "all": 75
    },
    "dt": 1740342294,
    "sys": {
        "type": 1,
        "id": 498,
        "country": "CA",
        "sunrise": 1740310980,
        "sunset": 1740349962
    },
    "timezone": -18000,
    "id": 6077243,
    "name": "Montreal",
    "cod": 200
}