{
    "coord": {
        "lon": -73.5878,
        "lat": 45.5088
    },
    "weather": [
        {
            "id": 803,
            "main": "Clouds",
            "description": "broken clouds",
            "icon": "04n"
        }
    ],
    "base": "stations",
    "main": {
        "temp": 20.67,
        "feels_like": 20.36,
        "temp_min": 18.9,
        "temp_max": 21.69,
        "pressure": 1011,
        "humidity": 60,
        "sea_level": 1011,
        "grnd_level": 1007
    },
    "visibility": 10000,
    "wind": {
        "speed": 6.69,
        "deg": 310,
        "gust": 9.77
    },
    "clouds": {
        "all": 75
    },
    "dt": 1751591836,
    "sys": {
        "type": 1,
        "id": 498,
        "country": "CA",
        "sunrise": 1751533842,
        "sunset": 1751589973
    },
    "timezone": -14400,
    "id": 6077243,
    "name": "Montreal",
    "cod": 200
}