{
    "coord": {
        "lon": -73.5878,
        "lat": 45.5088
    },
    "weather": [
        {
            "id": 801,
            "main": "Clouds",
            "description": "few clouds",
            "icon": "02n"
        }
    ],
    "base": "stations",
    "main": {
        "temp": 28.69,
        "feels_like": 29.86,
        "temp_min": 27.48,
        "temp_max": 29.68,
        "pressure": 1019,
        "humidity": 55,
        "sea_level": 1019,
        "grnd_level": 1015
    },
    "visibility": 10000,
    "wind": {
        "speed": 3.6,
        "deg": 180
    },
    "clouds": {
        "all": 20
    },
    "dt": 1754875909,
    "sys": {
        "type": 1,
        "id": 498,
        "country": "CA",
        "sunrise": 1754819354,
        "sunset": 1754871014
    },
    "timezone": -14400,
    "id": 6077243,
    "name": "Montreal",
    "cod": 200
}