{
    "coord": {
        "lon": -73.5878,
        "lat": 45.5088
    },
    "weather": [
        {
            "id": 600,
            "main": "Snow",
            "description": "light snow",
            "icon": "13d"
        }
    ],
    "base": "stations",
    "main": {
        "temp": -3.93,
        "feels_like": -8.78,
        "temp_min": -5.48,
        "temp_max": -1.63,
        "pressure": 1001,
        "humidity": 93,
        "sea_level": 1001,
        "grnd_level": 997
    },
    "visibility": 2414,
    "wind": {
        "speed": 3.6,
        "deg": 20
    },
    "snow": {
        "1h": 0.2
    },
    "clouds": {
        "all": 100
    },
    "dt": 1739478435,
    "sys": {
        "type": 1,
        "id": 498,
        "country": "CA",
        "sunrise": 1739447942,
        "sunset": 1739485098
    },
    "timezone": -18000,
    "id": 6077243,
    "name": "Montreal",
    "cod": 200
}